freelpipe/__init__.py
freelpipe/pipeline.py
freelpipe/workflow.py
freelpipe/ml/__init__.py
freelpipe/ml/estimator.py
freelpipe/ml/processor.py
freelpipe/ops/__init__.py
freelpipe/ops/config.py
freelpipe/steps/__init__.py
freelpipe/steps/compute.py
freelpipe/steps/ml.py
freelpipe-0.0.14.dist-info/METADATA
freelpipe-0.0.14.dist-info/WHEEL
freelpipe-0.0.14.dist-info/top_level.txt
freelpipe-0.0.14.dist-info/RECORD
