Metadata-Version: 2.1
Name: freelpipe
Version: 0.0.14
Summary: Freeldom package
Home-page: https://github.com/pypa/sampleproject
Author: Matthieu Blais
Author-email: matthieu@freeldom.com
License: UNKNOWN
Platform: UNKNOWN
Classifier: Programming Language :: Python :: 3
Classifier: License :: OSI Approved :: MIT License
Classifier: Operating System :: OS Independent
Requires-Python: >=3.6
Requires-Dist: pyaml (==20.4.0)
Requires-Dist: stepfunctions (==1.1.2)
